setup.py
tkPathBrowser/__init__.py
tkPathBrowser.egg-info/PKG-INFO
tkPathBrowser.egg-info/SOURCES.txt
tkPathBrowser.egg-info/dependency_links.txt
tkPathBrowser.egg-info/top_level.txt